{
    "config": {
        "iso": "2020-02-14T02:05:37.519192",
        "timestamp": 1581645937.519192
    },
    "db_type_mariadb": {
        "iso": "2020-02-14T02:05:39.334855",
        "timestamp": 1581645939.334855
    },
    "directory_structure": {
        "iso": "2020-02-14T02:05:37.690764",
        "timestamp": 1581645937.690764
    },
    "iana": {
        "iso": "2020-02-14T01:28:11.293670",
        "timestamp": 1581643691.29367
    },
    "psl": {
        "iso": "2020-02-14T01:28:11.444038",
        "timestamp": 1581643691.444038
    },
    "user_agents": {
        "iso": "2020-02-14T01:28:11.625831",
        "timestamp": 1581643691.625831
    }
}