{
    "config": {
        "iso": "2020-02-14T00:50:43.148899",
        "timestamp": 1581641443.148899
    },
    "db_type_mariadb": {
        "iso": "2020-02-14T01:28:13.347810",
        "timestamp": 1581643693.34781
    },
    "directory_structure": {
        "iso": "2020-02-14T00:50:43.243720",
        "timestamp": 1581641443.24372
    },
    "iana": {
        "iso": "2020-02-14T01:28:11.293670",
        "timestamp": 1581643691.29367
    },
    "psl": {
        "iso": "2020-02-14T01:28:11.444038",
        "timestamp": 1581643691.444038
    },
    "user_agents": {
        "iso": "2020-02-14T01:28:11.625831",
        "timestamp": 1581643691.625831
    }
}