{
    "config": {
        "iso": "2020-02-08T23:09:24.863079",
        "timestamp": 1581203364.863079
    },
    "db_type_mariadb": {
        "iso": "2020-02-08T23:09:26.864961",
        "timestamp": 1581203366.864961
    },
    "directory_structure": {
        "iso": "2020-02-08T23:09:25.190778",
        "timestamp": 1581203365.190778
    },
    "iana": {
        "iso": "2020-02-08T23:09:24.966661",
        "timestamp": 1581203364.966661
    },
    "psl": {
        "iso": "2020-02-08T23:09:25.044036",
        "timestamp": 1581203365.044036
    },
    "user_agents": {
        "iso": "2020-02-08T23:09:25.251993",
        "timestamp": 1581203365.251993
    }
}