{
    "config": {
        "iso": "2020-02-04T04:33:36.660204",
        "timestamp": 1580790816.660204
    },
    "db_type_mariadb": {
        "iso": "2020-02-04T05:14:08.545521",
        "timestamp": 1580793248.545521
    },
    "directory_structure": {
        "iso": "2020-02-04T04:33:36.911163",
        "timestamp": 1580790816.911163
    },
    "iana": {
        "iso": "2020-02-03T21:00:06.574143",
        "timestamp": 1580763606.574143
    },
    "psl": {
        "iso": "2020-02-03T21:00:06.727545",
        "timestamp": 1580763606.727545
    },
    "user_agents": {
        "iso": "2020-02-03T21:00:06.931021",
        "timestamp": 1580763606.931021
    }
}