{
    "config": {
        "iso": "2020-02-15T03:11:30.156944",
        "timestamp": 1581736290.156944
    },
    "db_type_mariadb": {
        "iso": "2020-02-15T03:11:32.111422",
        "timestamp": 1581736292.111422
    },
    "directory_structure": {
        "iso": "2020-02-15T03:11:30.243530",
        "timestamp": 1581736290.24353
    },
    "iana": {
        "iso": "2020-02-15T01:56:15.359723",
        "timestamp": 1581731775.359723
    },
    "psl": {
        "iso": "2020-02-15T01:56:15.528514",
        "timestamp": 1581731775.528514
    },
    "user_agents": {
        "iso": "2020-02-15T01:56:15.739982",
        "timestamp": 1581731775.739982
    }
}