{
    "config": {
        "iso": "2020-02-21T05:59:43.278038",
        "timestamp": 1582264783.278038
    },
    "db_type_mariadb": {
        "iso": "2020-02-21T06:37:22.890465",
        "timestamp": 1582267042.890465
    },
    "directory_structure": {
        "iso": "2020-02-21T05:59:43.430550",
        "timestamp": 1582264783.43055
    },
    "iana": {
        "iso": "2020-02-21T04:44:37.448257",
        "timestamp": 1582260277.448257
    },
    "psl": {
        "iso": "2020-02-21T04:44:37.628875",
        "timestamp": 1582260277.628875
    },
    "user_agents": {
        "iso": "2020-02-21T04:44:37.934856",
        "timestamp": 1582260277.934856
    }
}